estraces/__init__.py
estraces/_version.py
estraces/_legacy_formats/__init__.py
estraces/_legacy_formats/bin_format.py
estraces/_legacy_formats/ets_format.py
estraces/_legacy_formats/trace.py
estraces/_legacy_formats/trace_header_set.py
estraces/formats/__init__.py
estraces/formats/bin_extractor.py
estraces/formats/bin_format.py
estraces/formats/buffered_ets_writer.py
estraces/formats/concat_format.py
estraces/formats/ets_format.py
estraces/formats/ets_writer.py
estraces/formats/frames.py
estraces/formats/ram_format.py
estraces/formats/random_reader.py
estraces/formats/sqlite_format.py
estraces/formats/trs_format.py
estraces/traces/__init__.py
estraces/traces/_metaclass.py
estraces/traces/abstract_reader.py
estraces/traces/headers.py
estraces/traces/metadatas.py
estraces/traces/samples.py
estraces/traces/trace.py
estraces/traces/trace_header_set.py
estraces-1.9.10.dist-info/licenses/AUTHORS.md
estraces-1.9.10.dist-info/licenses/LICENSE
estraces-1.9.10.dist-info/METADATA
estraces-1.9.10.dist-info/WHEEL
estraces-1.9.10.dist-info/top_level.txt
estraces-1.9.10.dist-info/RECORD
