Metadata-Version: 2.4
Name: estraces
Version: 1.9.10
Summary: Traces and trace header set Python library for side-channel analysis.
Home-page: https://gitlab.com/eshard/estraces
Author: eshard
Author-email: estraces@eshard.com
Project-URL: eShard, https://www.eshard.com
Project-URL: Documentation, https://eshard.gitlab.io/estraces
Project-URL: Issues, https://gitlab.com/eshard/estraces/issues
Classifier: Programming Language :: Python :: 3.9
Classifier: Programming Language :: Python :: 3.10
Classifier: Programming Language :: Python :: 3.11
Classifier: Programming Language :: Python :: 3.12
Classifier: Development Status :: 5 - Production/Stable
Classifier: Environment :: Console
Classifier: Framework :: Jupyter
Classifier: Framework :: IPython
Classifier: Intended Audience :: Developers
Classifier: Intended Audience :: Information Technology
Classifier: Intended Audience :: Science/Research
Classifier: License :: OSI Approved :: GNU Lesser General Public License v3 (LGPLv3)
Classifier: Topic :: Scientific/Engineering
Classifier: Topic :: Security
Classifier: Topic :: Software Development
Classifier: Operating System :: OS Independent
Requires-Python: >=3.8.0
License-File: LICENSE
License-File: AUTHORS.md
Requires-Dist: numpy<2
Requires-Dist: h5py
Requires-Dist: trsfile
Requires-Dist: psutil
Provides-Extra: test
Requires-Dist: pytest; extra == "test"
Requires-Dist: pytest-cov; extra == "test"
Requires-Dist: mock; extra == "test"
Requires-Dist: memory_profiler>=0.61.0; extra == "test"
Requires-Dist: cloudpickle; extra == "test"
Dynamic: license-file
